drf_pydantic/__init__.py
drf_pydantic/base_model.py
drf_pydantic/base_serializer.py
drf_pydantic/config.py
drf_pydantic/errors.py
drf_pydantic/parse.py
drf_pydantic/py.typed
drf_pydantic/utils.py
drf_pydantic-2.9.1.dist-info/METADATA
drf_pydantic-2.9.1.dist-info/WHEEL
drf_pydantic-2.9.1.dist-info/licenses/LICENSE
drf_pydantic-2.9.1.dist-info/RECORD
