Metadata-Version: 2.4
Name: drf-pydantic
Version: 2.9.1
Summary: Use pydantic with the Django REST framework
Project-URL: homepage, https://github.com/georgebv/drf-pydantic
Project-URL: github, https://github.com/georgebv/drf-pydantic
Author-email: George Bocharov <bocharovgeorgii@gmail.com>
License-Expression: MIT
License-File: LICENSE
Keywords: api,django,drf,pydantic,rest,typing
Classifier: Development Status :: 5 - Production/Stable
Classifier: Intended Audience :: Developers
Classifier: Intended Audience :: Information Technology
Classifier: Intended Audience :: System Administrators
Classifier: License :: OSI Approved :: MIT License
Classifier: Operating System :: OS Independent
Classifier: Programming Language :: Python
Classifier: Programming Language :: Python :: 3
Classifier: Programming Language :: Python :: 3 :: Only
Classifier: Programming Language :: Python :: 3.9
Classifier: Programming Language :: Python :: 3.10
Classifier: Programming Language :: Python :: 3.11
Classifier: Programming Language :: Python :: 3.12
Classifier: Programming Language :: Python :: 3.13
Classifier: Topic :: Software Development :: Libraries :: Python Modules
Classifier: Typing :: Typed
Requires-Python: >=3.9
Requires-Dist: djangorestframework>=3.13.0
Requires-Dist: pydantic[email]>=2.0.0
